finrich/__init__.py
finrich/finrich.py
finrich-0.3.2.dist-info/LICENSE
finrich-0.3.2.dist-info/METADATA
finrich-0.3.2.dist-info/WHEEL
finrich-0.3.2.dist-info/entry_points.txt
finrich-0.3.2.dist-info/top_level.txt
finrich-0.3.2.dist-info/RECORD
