Metadata-Version: 2.1
Name: finrich
Version: 0.3.2
Summary: Calculate enrichment of genomic regions with fine-mapping signals
Home-page: https://gitlab.com/aaylward/finrich
Author: Anthony Aylward
Author-email: aaylward@salk.edu
License: UNKNOWN
Platform: UNKNOWN
Classifier: Programming Language :: Python :: 3
Classifier: License :: OSI Approved :: MIT License
Classifier: Operating System :: OS Independent
License-File: LICENSE
Requires-Dist: pybedtools
Requires-Dist: scipy
